DLLBridge/__init__.py
DLLBridge-0.1.0.dist-info/METADATA
DLLBridge-0.1.0.dist-info/WHEEL
DLLBridge-0.1.0.dist-info/top_level.txt
DLLBridge-0.1.0.dist-info/RECORD
