Metadata-Version: 2.1
Name: DLLBridge
Version: 0.1.0
Summary: A simple Python library to interact with DLLs on Windows.
Author: Leonardo
Author-email: leonardonery616@gmail.com
Classifier: Programming Language :: Python :: 3
Classifier: License :: OSI Approved :: MIT License
Classifier: Operating System :: Microsoft :: Windows
Classifier: Intended Audience :: Developers
Requires-Python: >=3.6
